{
  "browser-harness": {
    "archived_at": null,
    "created_at": "2026-05-03T01:52:15.887993+00:00",
    "last_patched_at": "2026-05-03T05:24:28.207640+00:00",
    "last_used_at": "2026-05-03T15:20:03.912931+00:00",
    "last_viewed_at": "2026-05-03T15:20:03.910733+00:00",
    "patch_count": 3,
    "pinned": false,
    "state": "active",
    "use_count": 6,
    "view_count": 6
  },
  "hermes-autoresearch": {
    "archived_at": null,
    "created_at": "2026-05-03T19:05:17.552916+00:00",
    "last_patched_at": null,
    "last_used_at": "2026-05-03T19:05:17.555558+00:00",
    "last_viewed_at": "2026-05-03T19:05:17.552943+00:00",
    "patch_count": 0,
    "pinned": false,
    "state": "active",
    "use_count": 1,
    "view_count": 1
  }
}